ImageAlgoKD/DataStructure.py
ImageAlgoKD/ImageAlgoKD.py
ImageAlgoKD/ImageAlgoKD_kernel_cuda.py
ImageAlgoKD/ImageAlgoKD_kernel_opencl.py
ImageAlgoKD/Utilities.py
ImageAlgoKD/__init__.py
ImageAlgoKD-0.0.4.dist-info/LICENSE
ImageAlgoKD-0.0.4.dist-info/METADATA
ImageAlgoKD-0.0.4.dist-info/WHEEL
ImageAlgoKD-0.0.4.dist-info/top_level.txt
ImageAlgoKD-0.0.4.dist-info/RECORD
