Metadata-Version: 2.1
Name: ImageAlgoKD
Version: 0.0.4
Summary: GPU implementation of clustering by fast search and find density peak.
Home-page: https://github.com/ZihengChen/ImageAlgorithm
Author: Ziheng Chen
Author-email: zihengchen2015@u.northwestern.edu
License: UNKNOWN
Platform: UNKNOWN
Classifier: Programming Language :: Python :: 3
Classifier: License :: OSI Approved :: MIT License
Classifier: Operating System :: OS Independent
